lmot/__init__.py
lmot/args.py
lmot/optimize.py
lmot/quantize/__init__.py
lmot/quantize/awq.py
lmot/quantize/common.py
lmot/quantize/gptq.py
lmot/quantize/smoothquant.py
lmot/quantize/test.py
lmot/quantize/utils.py
lmot/quantize/ldm/__init__.py
lmot/quantize/ldm/controlnet_quant.py
lmot/quantize/ldm/ldm_calib.py
lmot/quantize/ldm/ldm_quant.py
lmot/quantize/ldm/test.py
lmot/quantize/ldm/transformers_quant.py
lmot/quantize/ldm/unet_quant.py
lmot/quantize/ldm/utils.py
lmot/sparse/__init__.py
lmot/specul/__init__.py
lmot/specul/configs.py
lmot/specul/eagle.py
lmot/specul/medusa.py
lmot/specul/utils.py
lmot-0.1.1.dist-info/METADATA
lmot-0.1.1.dist-info/WHEEL
lmot-0.1.1.dist-info/top_level.txt
lmot-0.1.1.dist-info/RECORD
